{
  "dataset_name": "contemporary_dance",
  "related_publication": "TODO",
  "location": "data/datasets/bvh",
  "format": "bvh",
  "fps": 60,
  "feet_info": {
    "left_idx": [4, 5],
    "right_idx": [9, 10]
  },
  "train_config": {
    "window": null,
    "offset": 10,
    "start_frame": 0,
    "shuffle": false,
    "file_matcher": "prefix",
    "match_values": [
      "Andria_Bored_v1-01_60fps"
    ]
  },
  "test_config": {
    "window": 65,
    "offset": 40,
    "start_frame": 0,
    "shuffle": false,
    "file_matcher": "prefix",
    "match_values": [
      "Andria_Bored_v1-01_60fps"
    ]
  },
  "preprocessing_config": {
    "start_centered": true,
    "skeleton_scale": 1
  }
}